<?xml version="1.0" encoding="UTF-8" standalone="yes"?>
<menus>
<menu>
<title>[COLOR gold]Aguianegra[/COLOR]»»[COLORchocolate] A Volta do Monstro do Pântano [/COLOR]</title>
<link> plugin://plugin.video.elementum/play?uri=magnet:?xt=urn:btih:cb9e8b92b8cf98b6e69608f4f32f1b85e3b2e05e</link>
<thumbnail>https://i.imgur.com/BHapTdq.jpg</thumbnail>
<fanart>https://i.imgur.com/iUsPzoW.jpg</fanart>
</menu>
<menu>
<title>[COLOR gold]Aguianegra[/COLOR]»»[COLORchocolate]Spawn O Soldado do Inferno  [/COLOR]</title>
<link> plugin://plugin.video.elementum/play?uri=magnet:?xt=urn:btih:35b3f92d95564033867b922477d373039860f970</link>
<thumbnail>https://i.imgur.com/o00oOkU.jpg</thumbnail>
<fanart>https://i.imgur.com/iUsPzoW.jpg</fanart>
</menu>
<menu>
<title>[COLOR gold]Aguianegra[/COLOR]»»[COLORchocolate] Man's Best Friend  [/COLOR]</title>
<link> plugin://plugin.video.elementum/play?uri=magnet:?xt=urn:btih:09ABDC63B657711D252255CC4731D22747EA79D8</link>
<thumbnail>https://i.imgur.com/UHSFGes.jpg</thumbnail>
<fanart>https://i.imgur.com/iUsPzoW.jpg</fanart>
</menu>
<menu>
<title>[COLOR gold]Aguianegra[/COLOR]»»[COLORchocolate] Yankee zulu  [/COLOR]</title>
<link> plugin://plugin.video.elementum/play?uri=magnet:?xt=urn:btih:D2473AFDD5D3D99C2E41C769B9DD4E6E2D9EFA4B</link>
<thumbnail>https://i.imgur.com/mgAsBgH.jpg</thumbnail>
<fanart>https://i.imgur.com/iUsPzoW.jpg</fanart>
</menu>
<menu>
<title>[COLOR gold]Aguianegra[/COLOR]»»[COLORchocolate]A corrida da bala de canhão [/COLOR]</title>
<link>plugin://plugin.video.elementum/play?uri=magnet:?xt=urn:btih:A59931DE7A1E89A55BBC78D01383511DF24533EC</link>
<thumbnail>https://i.imgur.com/OJq5lvv.jpg</thumbnail>
<fanart>https://i.imgur.com/iUsPzoW.jpg</fanart>
</menu>
<menu>
<title>[COLOR gold]Aguianegra[/COLOR]»»[COLORchocolate]Corrida de canhão II[/COLOR]</title>
<link>plugin://plugin.video.elementum/play?uri=magnet:?xt=urn:btih:C32CC114B6E444C8074A249BCCC38405C105A0C5</link>
<thumbnail>https://i.imgur.com/UMMu6aL.jpg</thumbnail>
<fanart>https://i.imgur.com/iUsPzoW.jpg</fanart>
</menu>
<menu>
<title>[COLOR gold]Aguianegra[/COLOR]»»[COLORchocolate]O fora da lei Josey Wales[/COLOR]</title>
<link>plugin://plugin.video.elementum/play?uri=magnet:?xt=urn:btih:AC710AF8F7425ADB690F41F34AF1073C159BA621</link>
<thumbnail>https://i.imgur.com/BPtjImu.jpg</thumbnail>
<fanart>https://i.imgur.com/iUsPzoW.jpg</fanart>
</menu>
<menu>
<title>[COLOR gold]Aguianegra[/COLOR]»»[COLORchocolate]O Incrível Burt Wonderstone[/COLOR]</title>
<link>plugin://plugin.video.elementum/play?uri=magnet:?xt=urn:btih:8AE55D032C6D750604F3374E11B7959ED28852FE</link>
<thumbnail>https://i.imgur.com/rNYZUmz.jpg</thumbnail>
<fanart>https://i.imgur.com/iUsPzoW.jpg</fanart>
</menu>
<menu>
<title>[COLOR gold]Aguianegra[/COLOR]»»[COLORchocolate]Prostitutas de motosserra de Hollywood[/COLOR]</title>
<link>plugin://plugin.video.elementum/play?uri=magnet:?xt=urn:btih:3E149F6B407ADAC413DA444BE19FAB94FAAC5380</link>
<thumbnail>https://i.imgur.com/SUFL3Jg.jpg</thumbnail>
<fanart>https://i.imgur.com/iUsPzoW.jpg</fanart>
</menu>
<menu>
<title>[COLOR gold]Aguianegra[/COLOR]»»[COLORchocolate]Guerras Sexuais de Hollywood[/COLOR]</title>
<link>plugin://plugin.video.elementum/play?uri=magnet:?xt=urn:btih:1B966F027348EE75C2E1CB0C9E89CCAC7DEF1CA1</link>
<thumbnail>https://i.imgur.com/17Arit0.jpg</thumbnail>
<fanart>https://i.imgur.com/iUsPzoW.jpg</fanart>
</menu>
<menu>
<title>[COLOR gold]Aguianegra[/COLOR]»»[COLORchocolate]Motosserra Texas[/COLOR]</title>
<link>plugin://plugin.video.elementum/play?uri=magnet:?xt=urn:btih:90D530609C3D9BD7EE22EA5C27A3307DEC5C56C8</link>
<thumbnail>https://i.imgur.com/yWBDRMa.jpg</thumbnail>
<fanart>https://i.imgur.com/iUsPzoW.jpg</fanart>
</menu>
<menu>
<title>[COLOR gold]Aguianegra[/COLOR]»»[COLORchocolate]O Massacre da Serra Elétrica: O Começo[/COLOR]</title>
<link>plugin://plugin.video.elementum/play?uri=magnet:?xt=urn:btih:A9D6BB8C146A8B44C71FC844372BFE72B91BDD0F</link>
<thumbnail>https://i.imgur.com/PgD4ki3.jpg</thumbnail>
<fanart>https://i.imgur.com/iUsPzoW.jpg</fanart>
</menu>
<menu>
<title>[COLOR gold]Aguianegra[/COLOR]»»[COLORchocolate]O massacre da Serra Elétrica do Texas[/COLOR]</title>
<link>plugin://plugin.video.elementum/play?uri=magnet:?xt=urn:btih:10D3CF7D2ECDFDD59A5F8B6A00AA0460C605296A</link>
<thumbnail>https://i.imgur.com/KJ7OL2x.jpg</thumbnail>
<fanart>https://i.imgur.com/iUsPzoW.jpg</fanart>
</menu>
<menu>
<title>[COLOR gold]Aguianegra[/COLOR]»»[COLORchocolate]Punho Imortal: A Lenda do Wing Chun[/COLOR]</title>
<link>plugin://plugin.video.elementum/play?uri=magnet:?xt=urn:btih:DC450960BBCBBA09B747C243B4B76CB1A687A6B1</link>
<thumbnail>https://i.imgur.com/dzbrokg.jpg</thumbnail>
<fanart>https://i.imgur.com/iUsPzoW.jpg</fanart>
</menu>
<menu>
<title>[COLOR gold]Aguianegra[/COLOR]»»[COLORchocolate]Imortal[/COLOR]</title>
<link>plugin://plugin.video.elementum/play?uri=magnet:?xt=urn:btih:F07012C4C59906BCB8AD91AA9449DB197453E820</link>
<thumbnail>https://i.imgur.com/44f52Gi.jpg</thumbnail>
<fanart>https://i.imgur.com/iUsPzoW.jpg</fanart>
</menu>
<menu>
<title>[COLOR gold]Aguianegra[/COLOR]»»[COLORchocolate]Mestre Z: Legado de Ip Man[/COLOR]</title>
<link>plugin://plugin.video.elementum/play?uri=magnet:?xt=urn:btih:C835E67F816896E49B03CAAB7CA0721EDF5E3223</link>
<thumbnail>https://i.imgur.com/THLID9j.jpg</thumbnail>
<fanart>https://i.imgur.com/iUsPzoW.jpg</fanart>
</menu>
<menu>
<title>[COLOR gold]Aguianegra[/COLOR]»»[COLORchocolate]Lago Placid[/COLOR]</title>
<link>plugin://plugin.video.elementum/play?uri=magnet:?xt=urn:btih:8767E10CB86B084798F99395E6456837D4BCD342</link>
<thumbnail>https://i.imgur.com/GRRdLlU.jpg</thumbnail>
<fanart>https://i.imgur.com/iUsPzoW.jpg</fanart>
</menu>
<menu>
<title>[COLOR gold]Aguianegra[/COLOR]»»[COLORchocolate]Um toque de Zen[/COLOR]</title>
<link>plugin://plugin.video.elementum/play?uri=magnet:?xt=urn:btih:12BD6E0EC8DF87BC4EC7C21F22542DDF4ECEBC49</link>
<thumbnail>https://i.imgur.com/XYvupZr.jpg</thumbnail>
<fanart>https://i.imgur.com/iUsPzoW.jpg</fanart>
</menu>
<menu>
<title>[COLOR gold]Aguianegra[/COLOR]»»[COLORchocolate]Animal[/COLOR]</title>
<link>plugin://plugin.video.elementum/play?uri=magnet:?xt=urn:btih:CE782B45BC75C853BA18F8179A64AEB086FF5FD2</link>
<thumbnail>https://i.imgur.com/CjpUEYj.jpg</thumbnail>
<fanart>https://i.imgur.com/iUsPzoW.jpg</fanart>
</menu>
<menu>
<title>[COLOR gold]Aguianegra[/COLOR]»»[COLORchocolate]Os alpinistas[/COLOR]</title>
<link>plugin://plugin.video.elementum/play?uri=magnet:?xt=urn:btih:E65AB948127C55B2A588095E5EF383C20669320A</link>
<thumbnail>https://i.imgur.com/Vt4VVKx.jpg</thumbnail>
<fanart>https://i.imgur.com/iUsPzoW.jpg</fanart>
</menu>
<menu>
<title>[COLOR gold]Aguianegra[/COLOR]»»[COLORchocolate]O boxeador espiritual[/COLOR]</title>
<link>plugin://plugin.video.elementum/play?uri=magnet:?xt=urn:btih:399EB98A79D75B068D3BD472D5C63192BB930C59</link>
<thumbnail>https://i.imgur.com/akHDV9f.png</thumbnail>
<fanart>https://i.imgur.com/iUsPzoW.jpg</fanart>
</menu>
<menu>
<title>[COLOR gold]Aguianegra[/COLOR]»»[COLORchocolate]Porto de escala[/COLOR]</title>
<link>plugin://plugin.video.elementum/play?uri=magnet:?xt=urn:btih:3D4E8A160870D3A3410090D7B77CE951FF34A96B</link>
<thumbnail>https://i.imgur.com/TkUtHkN.jpg</thumbnail>
<fanart>https://i.imgur.com/iUsPzoW.jpg</fanart>
</menu>
<menu>
<title>[COLOR gold]Aguianegra[/COLOR]»»[COLORchocolate]Crianças de Shaolin[/COLOR]</title>
<link>plugin://plugin.video.elementum/play?uri=magnet:?xt=urn:btih:0EF1C3A962D4853642DFA7E4DBC5DDB04976C23C</link>
<thumbnail>https://i.imgur.com/xsT6skd.jpg</thumbnail>
<fanart>https://i.imgur.com/iUsPzoW.jpg</fanart>
</menu>
<menu>
<title>[COLOR gold]Aguianegra[/COLOR]»»[COLORchocolate]jogador Shaolin[/COLOR]</title>
<link>plugin://plugin.video.elementum/play?uri=magnet:?xt=urn:btih:3035785C35C5845A2F7A0327873BCD5F672CF5A0</link>
<thumbnail>https://i.imgur.com/yGZohmR.jpg</thumbnail>
<fanart>https://i.imgur.com/iUsPzoW.jpg</fanart>
</menu>
<menu>
<title>[COLOR gold]Aguianegra[/COLOR]»»[COLORchocolate]A 36ª Câmara de Shaolin[/COLOR]</title>
<link>plugin://plugin.video.elementum/play?uri=magnet:?xt=urn:btih:8B5806A2A2564CD04AB5D7B8B6F9EBBB953BF7BB</link>
<thumbnail>https://i.imgur.com/pIVXQPP.jpg</thumbnail>
<fanart>https://i.imgur.com/iUsPzoW.jpg</fanart>
</menu>
<menu>
<title>[COLOR gold]Aguianegra[/COLOR]»»[COLORchocolate]Mestre de espada[/COLOR]</title>
<link>plugin://plugin.video.elementum/play?uri=magnet:?xt=urn:btih:16A6FB5D0F8E243EAB3B5D60E64FF0268EB3AA46</link>
<thumbnail>https://i.imgur.com/tttqxBx.jpg</thumbnail>
<fanart>https://i.imgur.com/iUsPzoW.jpg</fanart>
</menu>
<menu>
<title>[COLOR gold]Aguianegra[/COLOR]»»[COLORchocolate]Memórias da Espada[/COLOR]</title>
<link>plugin://plugin.video.elementum/play?uri=magnet:?xt=urn:btih:446245674796D82527EDB557EAB866D601800C0F</link>
<thumbnail>https://i.imgur.com/MBfnGWi.jpg</thumbnail>
<fanart>https://i.imgur.com/iUsPzoW.jpg</fanart>
</menu>
<menu>
<title>[COLOR gold]Aguianegra[/COLOR]»»[COLORchocolate]Mestre de Tai Chi[/COLOR]</title>
<link>plugin://plugin.video.elementum/play?uri=magnet:?xt=urn:btih:8BB57F64D3971D97CD7D4D5DBE71D061385BBBA2</link>
<thumbnail>https://i.imgur.com/tttqxBx.jpg</thumbnail>
<fanart>https://i.imgur.com/iUsPzoW.jpg</fanart>
</menu>
<menu>
<title>[COLOR gold]Aguianegra[/COLOR]»»[COLORchocolate]Rainha Bárbara[/COLOR]</title>
<link>plugin://plugin.video.elementum/play?uri=magnet:?xt=urn:btih:11EE8FF31878083F6E6B5A3EAA01DACE45A4A9AD</link>
<thumbnail>https://i.imgur.com/fu7zwwW.jpg</thumbnail>
<fanart>https://i.imgur.com/iUsPzoW.jpg</fanart>
</menu>
<menu>
<title>[COLOR gold]Aguianegra[/COLOR]»»[COLORchocolate]Amanhecer Vermelho[/COLOR]</title>
<link>plugin://plugin.video.elementum/play?uri=magnet:?xt=urn:btih:AEBE9B5227318748452962D610F9057CDD10ACEA</link>
<thumbnail>https://i.imgur.com/CodiKjY.jpg</thumbnail>
<fanart>https://i.imgur.com/iUsPzoW.jpg</fanart>
</menu>
<menu>
<title>[COLOR gold]Aguianegra[/COLOR]»»[COLORchocolate]Soldado[/COLOR]</title>
<link>plugin://plugin.video.elementum/play?uri=magnet:?xt=urn:btih:EAA48BB35A643FCAFEE811937D09162BEA237793</link>
<thumbnail>https://i.imgur.com/69UlG7I.jpg</thumbnail>
<fanart>https://i.imgur.com/iUsPzoW.jpg</fanart>
</menu>
<menu>
<title>[COLOR gold]Aguianegra[/COLOR]»»[COLORchocolate]menina do soldado[/COLOR]</title>
<link>plugin://plugin.video.elementum/play?uri=magnet:?xt=urn:btih:55DB50FE1D82E988FB40913D70B0D84BAA5CF701</link>
<thumbnail>https://i.imgur.com/kNaVVKC.jpg</thumbnail>
<fanart>https://i.imgur.com/iUsPzoW.jpg</fanart>
</menu>
<menu>
<title>[COLOR gold]Aguianegra[/COLOR]»»[COLORchocolate]Matar todos eles[/COLOR]</title>
<link>plugin://plugin.video.elementum/play?uri=magnet:?xt=urn:btih:AEB9563BA6227D9CF85C73388D533CF474ED4A5F</link>
<thumbnail>https://i.imgur.com/HkECmn1.jpg</thumbnail>
<fanart>https://i.imgur.com/iUsPzoW.jpg</fanart>
</menu>
<menu>
<title>[COLOR gold]Aguianegra[/COLOR]»»[COLORchocolate]Sobrecarga máxima[/COLOR]</title>
<link>plugin://plugin.video.elementum/play?uri=magnet:?xt=urn:btih:D4BD0B4071D2050D0EC01F7400B93F7EC8A71B5E</link>
<thumbnail>https://i.imgur.com/m7OISzF.jpg</thumbnail>
<fanart>https://i.imgur.com/iUsPzoW.jpg</fanart>
</menu>
<menu>
<title>[COLOR gold]Aguianegra[/COLOR]»»[COLORchocolate]Além do horizonte[/COLOR]</title>
<link>plugin://plugin.video.elementum/play?uri=magnet:?xt=urn:btih:7A06F38237DE5669216CBA7B859526E6A8007162</link>
<thumbnail>https://i.imgur.com/hZFCe7y.jpg</thumbnail>
<fanart>https://i.imgur.com/iUsPzoW.jpg</fanart>
</menu>
<menu>
<title>[COLOR gold]Aguianegra[/COLOR]»»[COLORchocolate]Revolta Alienígena[/COLOR]</title>
<link>plugin://plugin.video.elementum/play?uri=magnet:?xt=urn:btih:862EA4708356E88A8A70FB8D83DEB982E8332AEA</link>
<thumbnail>https://i.imgur.com/6GMRjaO.jpg</thumbnail>
<fanart>https://i.imgur.com/iUsPzoW.jpg</fanart>
</menu>
<menu>
<title>[COLOR gold]Aguianegra[/COLOR]»»[COLORchocolate]Pastor Pastor[/COLOR]</title>
<link>plugin://plugin.video.elementum/play?uri=magnet:?xt=urn:btih:8F062387DE83C2BC15CBFFA2E8FE3F7B90EAE284</link>
<thumbnail>https://i.imgur.com/ynuLc3d.jpg</thumbnail>
<fanart>https://i.imgur.com/iUsPzoW.jpg</fanart>
</menu>
<menu>
<title>[COLOR gold]Aguianegra[/COLOR]»»[COLORchocolate]Street Fighter Punho do Assassino[/COLOR]</title>
<link>plugin://plugin.video.elementum/play?uri=magnet:?xt=urn:btih:4E2370F10BB0392CD7D2B9AA6DB5BC3665DBD343</link>
<thumbnail>https://i.imgur.com/JocOYkK.jpg</thumbnail>
<fanart>https://i.imgur.com/iUsPzoW.jpg</fanart>
</menu>
<menu>
<title>[COLOR gold]Aguianegra[/COLOR]»»[COLORchocolate]O Retorno da Irmã Street Fighter[/COLOR]</title>
<link>plugin://plugin.video.elementum/play?uri=magnet:?xt=urn:btih:2C7BC183BEE1FA2F597EA3C95D5C930E637B9DEB</link>
<thumbnail>https://i.imgur.com/ZmTM4aK.jpg</thumbnail>
<fanart>https://i.imgur.com/iUsPzoW.jpg</fanart>
</menu>
<menu>
<title>[COLOR gold]Aguianegra[/COLOR]»»[COLORchocolate]Lei marcial[/COLOR]</title>
<link>plugin://plugin.video.elementum/play?uri=magnet:?xt=urn:btih:1F562BC8FC244F2101E142CE346BB53DB269D0F8</link>
<thumbnail>https://i.imgur.com/JAYNpS1.jpg</thumbnail>
<fanart>https://i.imgur.com/iUsPzoW.jpg</fanart>
</menu>
<menu>
<title>[COLOR gold]Aguianegra[/COLOR]»»[COLORchocolate]Lei Marcial 2 Disfarçado[/COLOR]</title>
<link>plugin://plugin.video.elementum/play?uri=magnet:?xt=urn:btih:18811AFECA935A88914BD0A842B9753635E8A48B</link>
<thumbnail>https://i.imgur.com/9gh4j2S.jpg</thumbnail>
<fanart>https://i.imgur.com/iUsPzoW.jpg</fanart>
</menu>
<menu>
<title>[COLOR gold]Aguianegra[/COLOR]»»[COLORchocolate]Missão de Justiça 3[/COLOR]</title>
<link>plugin://plugin.video.elementum/play?uri=magnet:?xt=urn:btih:f5f4ecfeeff545e1747ab2ac754ec9f0be0ef67c</link>
<thumbnail>https://i.imgur.com/L7mn0tY.jpg</thumbnail>
<fanart>https://i.imgur.com/iUsPzoW.jpg</fanart>
</menu>
<menu>
<title>[COLOR gold]Aguianegra[/COLOR]»»[COLORchocolate]Jurado à Justiça[/COLOR]</title>
<link>plugin://plugin.video.elementum/play?uri=magnet:?xt=urn:btih:4AA93857B03C0A65D52A23C4AEDA6A0A16F64912</link>
<thumbnail>https://i.imgur.com/mmMa2Zc.jpg</thumbnail>
<fanart>https://i.imgur.com/iUsPzoW.jpg</fanart>
</menu>
<menu>
<title>[COLOR gold]Aguianegra[/COLOR]»»[COLORchocolate]Huff[/COLOR]</title>
<link>plugin://plugin.video.elementum/play?uri=magnet:?xt=urn:btih:33A09326FD745268BB6C05D0F287E1E31584EB96</link>
<thumbnail>https://i.imgur.com/sjf63L1.jpg</thumbnail>
<fanart>https://i.imgur.com/iUsPzoW.jpg</fanart>
</menu>
<menu>
<title>[COLOR gold]Aguianegra[/COLOR]»»[COLORchocolate]Sair da humanidade[/COLOR]</title>
<link>plugin://plugin.video.elementum/play?uri=magnet:?xt=urn:btih:4E983FC38672BE8D2A1BD9896577378B1E0C10A2</link>
<thumbnail>https://i.imgur.com/2be8qAj.jpg</thumbnail>
<fanart>https://i.imgur.com/iUsPzoW.jpg</fanart>
</menu>
<menu>
<title>[COLOR gold]Aguianegra[/COLOR]»»[COLORchocolate]Loaded Weapon 1[/COLOR]</title>
<link>plugin://plugin.video.elementum/play?uri=magnet:?xt=urn:btih:B09B679CFF9565DED2FA6C6029484C2584EBE5AC</link>
<thumbnail>https://i.imgur.com/gavVW9V.jpg</thumbnail>
<fanart>https://i.imgur.com/iUsPzoW.jpg</fanart>
</menu>
<menu>
<title>[COLOR gold]Aguianegra[/COLOR]»»[COLORchocolate]Yakuza Weapon[/COLOR]</title>
<link>plugin://plugin.video.elementum/play?uri=magnet:?xt=urn:btih:EEACBC6421900AC66720B99EE425FC0E258C1ECD</link>
<thumbnail>https://i.imgur.com/SgnrSlY.jpg</thumbnail>
<fanart>https://i.imgur.com/iUsPzoW.jpg</fanart>
</menu>
<menu>
<title>[COLOR gold]Aguianegra[/COLOR]»»[COLORchocolate]The Perfect Weapon[/COLOR]</title>
<link>plugin://plugin.video.elementum/play?uri=magnet:?xt=urn:btih:7099A42E0476BF191BCD456A9805EF10182054F3</link>
<thumbnail>https://i.imgur.com/twnCzhE.jpg</thumbnail>
<fanart>https://i.imgur.com/iUsPzoW.jpg</fanart>
</menu>
<menu>
<title>[COLOR gold]Aguianegra[/COLOR]»»[COLORchocolate]Easy Money II: Hard to Kill[/COLOR]</title>
<link>plugin://plugin.video.elementum/play?uri=magnet:?xt=urn:btih:BFDCE2A3A4CB5AB730358BE07301BCF46603ABCE</link>
<thumbnail>https://i.imgur.com/QTrT7A4.jpg</thumbnail>
<fanart>https://i.imgur.com/iUsPzoW.jpg</fanart>
</menu>
<menu>
<title>[COLOR gold]Aguianegra[/COLOR]»»[COLORchocolate]The Hard Way[/COLOR]</title>
<link>plugin://plugin.video.elementum/play?uri=magnet:?xt=urn:btih:000CD550FFA7177765B17D5AD3E5C9B8945BBF84</link>
<thumbnail>https://i.imgur.com/UqbOjQo.jpg</thumbnail>
<fanart>https://i.imgur.com/iUsPzoW.jpg</fanart>
</menu>
<menu>
<title>[COLOR gold]Aguianegra[/COLOR]»»[COLORchocolate]Blunt Force Trauma[/COLOR]</title>
<link>plugin://plugin.video.elementum/play?uri=magnet:?xt=urn:btih:B1B9222F922BD0673920D5DD299ED04ED2A36FB0</link>
<thumbnail>https://i.imgur.com/pmI72oh.jpg</thumbnail>
<fanart>https://i.imgur.com/iUsPzoW.jpg</fanart>
</menu>
<menu>
<title>[COLOR gold]Aguianegra[/COLOR]»»[COLORchocolate]Catch Hell[/COLOR]</title>
<link>plugin://plugin.video.elementum/play?uri=magnet:?xt=urn:btih:A70A9AB94FB3BE1ADB2C494BDF2925AC66C8E175</link>
<thumbnail>https://i.imgur.com/EzwPJ7z.jpg</thumbnail>
<fanart>https://i.imgur.com/iUsPzoW.jpg</fanart>
</menu>
<menu>
<title>[COLOR gold]Aguianegra[/COLOR]»»[COLORchocolate]Starship Rising[/COLOR]</title>
<link>plugin://plugin.video.elementum/play?uri=magnet:?xt=urn:btih:6258CBBA24AC66EF2462BF9CB91210DCEB136CF7</link>
<thumbnail>https://i.imgur.com/elSaBL6.jpg</thumbnail>
<fanart>https://i.imgur.com/iUsPzoW.jpg</fanart>
</menu>
<menu>
<title>[COLOR gold]Aguianegra[/COLOR]»»[COLORchocolate]Predator[/COLOR]</title>
<link>plugin://plugin.video.elementum/play?uri=magnet:?xt=urn:btih:FB132F15FD902A715403C7F57025C3EEC86F77E5</link>
<thumbnail>https://i.imgur.com/NRsWNOL.jpg</thumbnail>
<fanart>https://i.imgur.com/iUsPzoW.jpg</fanart>
</menu>
<menu>
<title>[COLOR gold]Aguianegra[/COLOR]»»[COLORchocolate]Predator 2[/COLOR]</title>
<link>plugin://plugin.video.elementum/play?uri=magnet:?xt=urn:btih:4366A99AF18396D70311BF7DA00A34486DB86E10</link>
<thumbnail>https://i.imgur.com/7ldZnln.jpg</thumbnail>
<fanart>https://i.imgur.com/iUsPzoW.jpg</fanart>
</menu>
<menu>
<title>[COLOR gold]Aguianegra[/COLOR]»»[COLORchocolate]Predators[/COLOR]</title>
<link>plugin://plugin.video.elementum/play?uri="magnet:?xt=urn:btih:1F781B0C04C97B7A912352EC719489414EB99DFC</link>
<thumbnail>https://i.imgur.com/XYmN0ER.jpg</thumbnail>
<fanart>https://i.imgur.com/iUsPzoW.jpg</fanart>
</menu>
<menu>
<title>[COLOR gold]Aguianegra[/COLOR]»»[COLORchocolate]The Predator[/COLOR]</title>
<link>plugin://plugin.video.elementum/play?uri=magnet:?xt=urn:btih:449F4DDF1FB79C63F59243FD8DBFD843A92EE5CE</link>
<thumbnail>https://i.imgur.com/cwIKfT2.jpg</thumbnail>
<fanart>https://i.imgur.com/iUsPzoW.jpg</fanart>
</menu>
<menu>
<title>[COLOR gold]Aguianegra[/COLOR]»»[COLORchocolate]Noite em Fuga[/COLOR]</title>
<link>plugin://plugin.video.elementum/play?uri=magnet:?xt=urn:btih:9D535CC988C98BBC45630F0CD2EAC7021EAEC303</link>
<thumbnail>https://i.imgur.com/EyJviWR.jpg</thumbnail>
<fanart>https://i.imgur.com/iUsPzoW.jpg</fanart>
</menu>
<menu>
<title>[COLOR gold]Aguianegra[/COLOR]»»[COLORchocolate]A Lenda de Tarzan[/COLOR]</title>
<link>plugin://plugin.video.elementum/play?uri=magnet:?xt=urn:btih:B36113D00A92367893164D60C64A7F0A1736DC2C</link>
<thumbnail>https://i.imgur.com/7K6KY3k.jpg</thumbnail>
<fanart>https://i.imgur.com/iUsPzoW.jpg</fanart>
</menu>
<menu>
<title>[COLOR gold]Aguianegra[/COLOR]»»[COLORchocolate]The Last Dragon[/COLOR]</title>
<link>plugin://plugin.video.elementum/play?uri=magnet:?xt=urn:btih:CF07367EE5B7D7A0E5B46D2E5D0E35E6D9AE96AD</link>
<thumbnail>https://i.imgur.com/lDcZ8us.jpg</thumbnail>
<fanart>https://i.imgur.com/iUsPzoW.jpg</fanart>
</menu>
<menu>
<title>[COLOR gold]Aguianegra[/COLOR]»»[COLORchocolate]Red Dragon[/COLOR]</title>
<link>plugin://plugin.video.elementum/play?uri=magnet:?xt=urn:btih:B6EE18BFD6229D3F62FEFC1FA271799D8DF906FE</link>
<thumbnail>https://i.imgur.com/tP21q73.jpg</thumbnail>
<fanart>https://i.imgur.com/iUsPzoW.jpg</fanart>
</menu>
<menu>
<title>[COLOR gold]Aguianegra[/COLOR]»»[COLORchocolate]Red Dragon[/COLOR]</title>
<link>plugin://plugin.video.elementum/play?uri=magnet:?xt=urn:btih:49E641ED54E4CB7AD75EE5DB46A74697CFDC19C7</link>
<thumbnail>https://i.imgur.com/YGO0sJf.jpg</thumbnail>
<fanart>https://i.imgur.com/iUsPzoW.jpg</fanart>
</menu>
<menu>
<title>[COLOR gold]Aguianegra[/COLOR]»»[COLORchocolate]Black Cobra[/COLOR]</title>
<link>plugin://plugin.video.elementum/play?uri=magnet:?xt=urn:btih:604EB0A881CCC37FEF2AB693DF6AEDEFB63C1F34</link>
<thumbnail>https://i.imgur.com/BYDLyrV.jpg</thumbnail>
<fanart>https://i.imgur.com/iUsPzoW.jpg</fanart>
</menu>
<menu>
<title>[COLOR gold]Aguianegra[/COLOR]»»[COLORchocolate]Black Dog[/COLOR]</title>
<link>plugin://plugin.video.elementum/play?uri=magnet:?xt=urn:btih:0B5C29657BAF9877F07B531434BA8095E2CAA6D2</link>
<thumbnail>https://i.imgur.com/6HZDM34.jpg</thumbnail>
<fanart>https://i.imgur.com/iUsPzoW.jpg</fanart>
</menu>
<menu>
<title>[COLOR gold]Aguianegra[/COLOR]»»[COLORchocolate]Assassins Run[/COLOR]</title>
<link>plugin://plugin.video.elementum/play?uri=magnet:?xt=urn:btih:9300E5D90B18D2C00F88A72708B2074002E5124D</link>
<thumbnail>https://i.imgur.com/xOt8x9k.jpg</thumbnail>
<fanart>https://i.imgur.com/iUsPzoW.jpg</fanart>
</menu>
<menu>
<title>[COLOR gold]Aguianegra[/COLOR]»»[COLORchocolate]Watchmen[/COLOR]</title>
<link>plugin://plugin.video.elementum/play?uri=magnet:?xt=urn:btih:608F2DA6CA661CDA193803FB9471FF833C04F5CC</link>
<thumbnail>https://i.imgur.com/5bYQGyc.jpg</thumbnail>
<fanart>https://i.imgur.com/iUsPzoW.jpg</fanart>
</menu>
<menu>
<title>[COLOR gold]Aguianegra[/COLOR]»»[COLORchocolate]Unstoppable[/COLOR]</title>
<link>plugin://plugin.video.elementum/play?uri=magnet:?xt=urn:btih:F2D8FB64A97C415EBF4EF64A675BA57C156EB449</link>
<thumbnail>https://i.imgur.com/pgDhYUB.jpg</thumbnail>
<fanart>https://i.imgur.com/iUsPzoW.jpg</fanart>
</menu>
<menu>
<title>[COLOR gold]Aguianegra[/COLOR]»»[COLORchocolate]Flawless[/COLOR]</title>
<link>plugin://plugin.video.elementum/play?uri=magnet:?xt=urn:btih:7C38AB9BE19B45289BD6458C1E59E31077C8F705</link>
<thumbnail>https://i.imgur.com/sD7I5qX.jpg</thumbnail>
<fanart>https://i.imgur.com/iUsPzoW.jpg</fanart>
</menu>
<menu>
<title>[COLOR gold]Aguianegra[/COLOR]»»[COLORchocolate]Blood and Bone[/COLOR]</title>
<link>plugin://plugin.video.elementum/play?uri=magnet:?xt=urn:btih:8B0AB882818E664123D315EDB50D7B254D3C0D6C</link>
<thumbnail>https://i.imgur.com/2NfIon4.jpg</thumbnail>
<fanart>https://i.imgur.com/iUsPzoW.jpg</fanart>
</menu>
<menu>
<title>[COLOR gold]Aguianegra[/COLOR]»»[COLORchocolate]O Ringue[/COLOR]</title>
<link>plugin://plugin.video.elementum/play?uri=magnet:?xt=urn:btih:8CB54C18E2C3D354AFBB17A3EC616664EE4D7D79</link>
<thumbnail>https://i.imgur.com/xpciokB.jpg</thumbnail>
<fanart>https://i.imgur.com/iUsPzoW.jpg</fanart>
</menu>
<menu>
<title>[COLOR gold]Aguianegra[/COLOR]»»[COLORchocolate]Flight of the Phoenix[/COLOR]</title>
<link>plugin://plugin.video.elementum/play?uri=magnet:?xt=urn:btih:64E3637B6F68783B3D81911B18DB2DF049C68496</link>
<thumbnail>https://i.imgur.com/8MWwNRa.jpg</thumbnail>
<fanart>https://i.imgur.com/iUsPzoW.jpg</fanart>
</menu>
<menu>
<title>[COLOR gold]Aguianegra[/COLOR]»»[COLORchocolate]The Raid: Redemption[/COLOR]</title>
<link>plugin://plugin.video.elementum/play?uri=magnet:?xt=urn:btih:49E74B914876AD23503291A3CBCCC3B58DB339E7</link>
<thumbnail>https://i.imgur.com/aFR8AvZ.jpg</thumbnail>
<fanart>https://i.imgur.com/iUsPzoW.jpg</fanart>
</menu>
<menu>
<title>[COLOR gold]Aguianegra[/COLOR]»»[COLORchocolate]The Raid 2[/COLOR]</title>
<link>plugin://plugin.video.elementum/play?uri=magnet:?xt=urn:btih:E15CE089EEA4CB50EAE2A6D1A59BDD86FCB0EA1F</link>
<thumbnail>https://i.imgur.com/hKFDGMv.jpg</thumbnail>
<fanart>https://i.imgur.com/iUsPzoW.jpg</fanart>
</menu>
<menu>
<title>[COLOR gold]Aguianegra[/COLOR]»»[COLORchocolate]Ambushed[/COLOR]</title>
<link>plugin://plugin.video.elementum/play?uri=magnet:?xt=urn:btih:1AD16B4C8836B066EECE521DB4A7CE82309E9ED0</link>
<thumbnail>https://i.imgur.com/Cxbm7t0.jpg</thumbnail>
<fanart>https://i.imgur.com/iUsPzoW.jpg</fanart>
</menu>
</menus>
